berea/__init__.py
berea/bible.py
berea/cli.py
berea/render.py
berea/utils.py
berea/data/book_abbreviations.json
berea/data/step_bible_books.csv
berea-0.1.1.dist-info/METADATA
berea-0.1.1.dist-info/WHEEL
berea-0.1.1.dist-info/entry_points.txt
berea-0.1.1.dist-info/licenses/LICENSE
berea-0.1.1.dist-info/RECORD
