Metadata-Version: 2.4
Name: berea
Version: 0.1.1
Summary: Berea: A CLI for studying Scripture.
Project-URL: Homepage, https://github.com/JStadnik619/berea
Author: Jamie Stadnik
License-Expression: MIT
License-File: LICENSE
Keywords: bible,cli,find,lookup,reference,scripture,search,verse
Classifier: Intended Audience :: Religion
Classifier: License :: OSI Approved :: MIT License
Classifier: Operating System :: OS Independent
Classifier: Programming Language :: Python :: 3
Requires-Python: >=3.8
Provides-Extra: dev
Requires-Dist: pytest>=7.3.2; extra == 'dev'
